ast_import_checker/__init__.py
ast_import_checker/import_checker.py
ast_import_checker/import_test_1.py
ast_import_checker/import_test_2.py
ast_import_checker/import_test_3.py
ast_import_checker/import_test_4.py
ast_import_checker/import_test_5/__init__.py
ast_import_checker/import_test_5/import_test_5.py
ast_import_checker/import_test_6/__init__.py
ast_import_checker/import_test_6/import_test_6.py
ast_import_checker-0.1.1.dist-info/entry_points.txt
ast_import_checker-0.1.1.dist-info/LICENSE
ast_import_checker-0.1.1.dist-info/WHEEL
ast_import_checker-0.1.1.dist-info/METADATA
ast_import_checker-0.1.1.dist-info/RECORD
